[
    {
        "iteration": 1,
        "status": "COMMITTED",
        "reason": "feat(AI): Tự động cải tiến file main.py"
    },
    {
        "iteration": 2,
        "status": "COMMITTED",
        "reason": "feat(AI): Tự động cải tiến file main.py"
    },
    {
        "iteration": 3,
        "status": "COMMITTED",
        "reason": "feat(AI): Tự động cải tiến file main.py"
    },
    {
        "iteration": 4,
        "status": "NO_PROPOSAL",
        "reason": "AI không trả về nội dung theo định dạng <change>..."
    },
    {
        "iteration": 5,
        "status": "NO_PROPOSAL",
        "reason": "AI không trả về nội dung theo định dạng <change>..."
    },
    {
        "iteration": 6,
        "status": "COMMITTED",
        "reason": "Thêm một bình luận TODO để gợi ý cải tiến trong tương lai."
    },
    {
        "iteration": 7,
        "status": "NO_PROPOSAL",
        "reason": "AI không trả về nội dung theo định dạng <change>..."
    },
    {
        "iteration": 8,
        "status": "NO_PROPOSAL",
        "reason": "AI không trả về nội dung theo định dạng <change>..."
    },
    {
        "iteration": 9,
        "status": "NO_PROPOSAL",
        "reason": "AI không trả về nội dung theo định dạng <change>..."
    },
    {
        "iteration": 10,
        "status": "COMMITTED",
        "reason": "Thêm logging để ghi lại khi ứng dụng chạy."
    },
    {
        "iteration": 11,
        "status": "COMMITTED",
        "reason": "Thêm kiểm tra lỗi cho hàm run_application"
    },
    {
        "iteration": 12,
        "status": "COMMITTED",
        "reason": "Thêm logging để ghi lại lỗi cụ thể hơn."
    },
    {
        "iteration": 13,
        "status": "COMMITTED",
        "reason": "Thêm kiểm tra xem biến môi trường VERSION có tồn tại hay không trước khi in ra thông báo."
    },
    {
        "iteration": 14,
        "status": "COMMITTED",
        "reason": "Thêm logging để thông báo khi phiên bản được lấy từ biến môi trường."
    },
    {
        "iteration": 15,
        "status": "COMMITTED",
        "reason": "Thêm kiểm tra xem biến môi trường VERSION có phải là số nguyên hay không."
    },
    {
        "iteration": 16,
        "status": "COMMITTED",
        "reason": "Thêm logging để ghi lại phiên bản được sử dụng."
    },
    {
        "iteration": 17,
        "status": "COMMITTED",
        "reason": "Thêm logging khi phiên bản mặc định được sử dụng."
    },
    {
        "iteration": 18,
        "status": "COMMITTED",
        "reason": "Thêm logging khi ứng dụng kết thúc thành công."
    },
    {
        "iteration": 19,
        "status": "COMMITTED",
        "reason": "Thêm logging để ghi lại thông tin chi tiết hơn về biến môi trường VERSION."
    },
    {
        "iteration": 20,
        "status": "COMMITTED",
        "reason": "Thêm logging để ghi lại việc sử dụng phiên bản mặc định."
    }
]